rdyn/__init__.py
rdyn/__main__.py
rdyn/alg/RDyn.py
rdyn/alg/RDyn_v2.py
rdyn/alg/__init__.py
rdyn-0.3.1.dist-info/DESCRIPTION.rst
rdyn-0.3.1.dist-info/METADATA
rdyn-0.3.1.dist-info/RECORD
rdyn-0.3.1.dist-info/WHEEL
rdyn-0.3.1.dist-info/metadata.json
rdyn-0.3.1.dist-info/top_level.txt
utils/__init__.py
utils/prova.py
utils/stats.py
